{"textures":{"0":"modelengine:entity/wumpus","particle":"#0"},"elements":[{"from":[1.7976394,8.449109,13.0],"to":[3.7976394,13.44911,19.0],"faces":{"east":{"uv":[4.625,7.4375,5.0,7.75],"tintindex":0,"rotation":0,"texture":"#0"},"south":{"uv":[5.5,7.4375,5.625,7.75],"tintindex":0,"rotation":0,"texture":"#0"},"north":{"uv":[5.0,7.4375,5.125,7.75],"tintindex":0,"rotation":0,"texture":"#0"},"west":{"uv":[5.125,7.4375,5.5,7.75],"tintindex":0,"rotation":0,"texture":"#0"},"up":{"uv":[5.125,7.4375,5.0,7.0625],"tintindex":0,"rotation":0,"texture":"#0"},"down":{"uv":[5.25,7.0625,5.125,7.4375],"tintindex":0,"rotation":0,"texture":"#0"}}}],"display":{"head":{"rotation":[0.0,0.0,-132.5]},"firstperson_righthand":{"rotation":[0.0,0.0,-132.5]},"thirdperson_lefthand":{"rotation":[0.0,-0.0,132.5]},"firstperson_lefthand":{"rotation":[0.0,-0.0,132.5]},"fixed":{"rotation":[0.0,0.0,-132.5]},"ground":{"rotation":[0.0,0.0,-132.5]},"thirdperson_righthand":{"rotation":[0.0,0.0,-132.5]},"gui":{"rotation":[-150.0,-45.0,47.5]}}}